fizzure/__init__.py
fizzure/cli.py
fizzure/controller.py
fizzure/main.py
fizzure/models.py
fizzure/saves.py
fizzure/timer.py
tests/__init__.py
tests/test_cli.py
tests/test_controller.py
tests/test_main.py
tests/test_models.py
tests/test_timer.py
fizzure-0.1.0.dist-info/LICENSE
fizzure-0.1.0.dist-info/METADATA
fizzure-0.1.0.dist-info/WHEEL
fizzure-0.1.0.dist-info/entry_points.txt
fizzure-0.1.0.dist-info/top_level.txt
fizzure-0.1.0.dist-info/zip-safe
fizzure-0.1.0.dist-info/RECORD
